<?xml version="1.0" encoding="UTF-8" standalone="yes"?>
<p:notes xmlns:a="http://schemas.openxmlformats.org/drawingml/2006/main" xmlns:r="http://schemas.openxmlformats.org/officeDocument/2006/relationships" xmlns:p="http://schemas.openxmlformats.org/presentationml/2006/main"><p:cSld><p:spTree><p:nvGrpSpPr><p:cNvPr id="1" name=""/><p:cNvGrpSpPr/><p:nvPr/></p:nvGrpSpPr><p:grpSpPr><a:xfrm><a:off x="0" y="0"/><a:ext cx="0" cy="0"/><a:chOff x="0" y="0"/><a:chExt cx="0" cy="0"/></a:xfrm></p:grpSpPr><p:sp><p:nvSpPr><p:cNvPr id="2" name="Slide Image Placeholder 1"/><p:cNvSpPr><a:spLocks noGrp="1" noRot="1" noChangeAspect="1"/></p:cNvSpPr><p:nvPr><p:ph type="sldImg"/></p:nvPr></p:nvSpPr><p:spPr/></p:sp><p:sp><p:nvSpPr><p:cNvPr id="3" name="Notes Placeholder 2"/><p:cNvSpPr><a:spLocks noGrp="1"/></p:cNvSpPr><p:nvPr><p:ph type="body" idx="1"/></p:nvPr></p:nvSpPr><p:spPr/><p:txBody><a:bodyPr/><a:lstStyle/><a:p><a:r><a:rPr lang="ko-KR" altLang="ko-KR" sz="1800" dirty="0"><a:effectLst/><a:ea typeface="Calibri" panose="020F0502020204030204" pitchFamily="34" charset="0"/></a:rPr><a:t>관리자는 회원과 사업자를 관리하는 역할을 합니다</a:t></a:r><a:r><a:rPr lang="en-US" altLang="ko-KR" sz="1800" dirty="0"><a:effectLst/><a:ea typeface="Calibri" panose="020F0502020204030204" pitchFamily="34" charset="0"/></a:rPr><a:t>. </a:t></a:r><a:r><a:rPr lang="ko-KR" altLang="ko-KR" sz="1800" dirty="0"><a:effectLst/><a:ea typeface="Calibri" panose="020F0502020204030204" pitchFamily="34" charset="0"/></a:rPr><a:t>로그인 후 대시보드에서 회원 목록을 조회하고</a:t></a:r><a:r><a:rPr lang="en-US" altLang="ko-KR" sz="1800" dirty="0"><a:effectLst/><a:ea typeface="Calibri" panose="020F0502020204030204" pitchFamily="34" charset="0"/></a:rPr><a:t>, </a:t></a:r></a:p><a:p><a:r><a:rPr lang="ko-KR" altLang="ko-KR" sz="1800" dirty="0"><a:effectLst/><a:ea typeface="Calibri" panose="020F0502020204030204" pitchFamily="34" charset="0"/></a:rPr><a:t>사업자가 제출한 서류를 검토해 승인하거나 반려합니다</a:t></a:r><a:r><a:rPr lang="en-US" altLang="ko-KR" sz="1800" dirty="0"><a:effectLst/><a:ea typeface="Calibri" panose="020F0502020204030204" pitchFamily="34" charset="0"/></a:rPr><a:t>. </a:t></a:r></a:p><a:p><a:r><a:rPr lang="ko-KR" altLang="ko-KR" sz="1800" dirty="0"><a:effectLst/><a:ea typeface="Calibri" panose="020F0502020204030204" pitchFamily="34" charset="0"/></a:rPr><a:t>콘텐츠 관리에서는 등록된 상품을 검수하고 게시글과 신고 내역을 처리하며 공지사항을 등록합니다</a:t></a:r><a:r><a:rPr lang="en-US" altLang="ko-KR" sz="1800" dirty="0"><a:effectLst/><a:ea typeface="Calibri" panose="020F0502020204030204" pitchFamily="34" charset="0"/></a:rPr><a:t>. </a:t></a:r></a:p><a:p><a:r><a:rPr lang="ko-KR" altLang="ko-KR" sz="1800" dirty="0"><a:effectLst/><a:ea typeface="Calibri" panose="020F0502020204030204" pitchFamily="34" charset="0"/></a:rPr><a:t>운영 메뉴에서는 이벤트와 재능기부 신청을 승인하고</a:t></a:r><a:r><a:rPr lang="en-US" altLang="ko-KR" sz="1800" dirty="0"><a:effectLst/><a:ea typeface="Calibri" panose="020F0502020204030204" pitchFamily="34" charset="0"/></a:rPr><a:t>, </a:t></a:r><a:r><a:rPr lang="ko-KR" altLang="ko-KR" sz="1800" dirty="0"><a:effectLst/><a:ea typeface="Calibri" panose="020F0502020204030204" pitchFamily="34" charset="0"/></a:rPr><a:t>마지막으로 통계 대시보드를 통해 회원 및 매출 통계를 </a:t></a:r><a:endParaRPr lang="en-US" altLang="ko-KR" sz="1800" dirty="0"><a:effectLst/><a:ea typeface="Calibri" panose="020F0502020204030204" pitchFamily="34" charset="0"/></a:endParaRPr></a:p><a:p><a:r><a:rPr lang="ko-KR" altLang="ko-KR" sz="1800" dirty="0"><a:effectLst/><a:ea typeface="Calibri" panose="020F0502020204030204" pitchFamily="34" charset="0"/></a:rPr><a:t>한눈에 확인할 수 있습니다</a:t></a:r><a:r><a:rPr lang="en-US" altLang="ko-KR" sz="1800" dirty="0"><a:effectLst/><a:ea typeface="Calibri" panose="020F0502020204030204" pitchFamily="34" charset="0"/></a:rPr><a:t>.</a:t></a:r><a:endParaRPr lang="en-US" dirty="0"/></a:p></p:txBody></p:sp><p:sp><p:nvSpPr><p:cNvPr id="4" name="Slide Number Placeholder 3"/><p:cNvSpPr><a:spLocks noGrp="1"/></p:cNvSpPr><p:nvPr><p:ph type="sldNum" sz="quarter" idx="10"/></p:nvPr></p:nvSpPr><p:spPr/><p:txBody><a:bodyPr/><a:lstStyle/><a:p><a:fld id="{F7021451-1387-4CA6-816F-3879F97B5CBC}" type="slidenum"><a:rPr lang="en-US"/><a:t>6</a:t></a:fld><a:endParaRPr lang="en-US"/></a:p></p:txBody></p:sp></p:spTree><p:extLst><p:ext uri="{BB962C8B-B14F-4D97-AF65-F5344CB8AC3E}"><p14:creationId xmlns:p14="http://schemas.microsoft.com/office/powerpoint/2010/main" val="1024086991"/></p:ext></p:extLst></p:cSld><p:clrMapOvr><a:masterClrMapping/></p:clrMapOvr></p:notes>